{
  "FormatVersion": "OOS-2019-06-01",
  "Description": "Deletes ECS instance by specifying instance ID.",
  "Parameters": {
    "instanceId": {
      "Description": "The ID of ECS instance.",
      "Type": "String",
      "MinLength": 1,
      "MaxLength": 30
    }
  },
  "Tasks": [
    {
      "Name": "checkInstanceReady",
      "Action": "ACS::CheckFor",
      "Description": "Checks ECS instance is in the Stopped status.",
      "Properties": {
        "Service": "ECS",
        "API": "DescribeInstances",
        "Parameters": {
          "InstanceIds": [
            "{{ instanceId }}"
          ]
        },
        "DesiredValues": [
          "Stopped"
        ],
        "PropertySelector": "Instances.Instance[].Status"
      }
    },
    {
      "Name": "deleteInstance",
      "Action": "ACS::ExecuteAPI",
      "Description": "Deletes ECS instance with the specified instance ID.",
      "Properties": {
        "Service": "ECS",
        "API": "DeleteInstance",
        "Parameters": {
          "InstanceId": "{{ instanceId }}"
        }
      }
    }
  ]
}